membrane/__init__.py
membrane/error_handler.py
membrane/membrane.py
membrane-0.0.4.dist-info/LICENSE
membrane-0.0.4.dist-info/METADATA
membrane-0.0.4.dist-info/WHEEL
membrane-0.0.4.dist-info/top_level.txt
membrane-0.0.4.dist-info/RECORD
