Metadata-Version: 2.1
Name: membrane
Version: 0.0.4
Summary: A Flask and Flask-RESTful argument parser.
Home-page: https://github.com/jscul/membrane.py
Author: jscul
Author-email: cullen.scott.john@gmail.com
License: UNKNOWN
Platform: UNKNOWN
Classifier: Programming Language :: Python :: 3
Classifier: License :: OSI Approved :: MIT License
Classifier: Operating System :: OS Independent
Requires-Python: >=3.6
